LICENSE
README.md
pyproject.toml
setup.cfg
setup.py
pyuname/__init__.py
pyuname/pyuname.py
pyuname.egg-info/PKG-INFO
pyuname.egg-info/SOURCES.txt
pyuname.egg-info/dependency_links.txt
pyuname.egg-info/not-zip-safe
pyuname.egg-info/top_level.txt