Metadata-Version: 2.1
Name: pyuname
Version: 0.0.1
Summary: This is a dumb library for uname
Home-page: UNKNOWN
Author-email: sdivcom@yandex.ru
License: UNKNOWN
Platform: UNKNOWN
License-File: LICENSE
